CHANGES.rst
LICENSE
MANIFEST.in
README.rst
setup.py
pierky/__init__.py
pierky/p2es/__init__.py
pierky/p2es/errors.py
pierky/p2es/es.py
pierky/p2es/readers.py
pierky/p2es/threads.py
pierky/p2es/transformations.py
pierky/p2es/version.py
pierky/p2es/writers.py
pmacct_to_elasticsearch.egg-info/PKG-INFO
pmacct_to_elasticsearch.egg-info/SOURCES.txt
pmacct_to_elasticsearch.egg-info/dependency_links.txt
pmacct_to_elasticsearch.egg-info/namespace_packages.txt
pmacct_to_elasticsearch.egg-info/requires.txt
pmacct_to_elasticsearch.egg-info/top_level.txt
scripts/pmacct-to-elasticsearch