Metadata-Version: 1.1
Name: pmacct-to-elasticsearch
Version: 0.3.1
Summary: A Python script designed to read output from pmacct daemons, to process it and to store it into ElasticSearch.
Home-page: https://github.com/pierky/pmacct-to-elasticsearch
Author: Pier Carlo Chiodi
Author-email: pierky@pierky.com
License: MIT
Download-URL: https://github.com/pierky/pmacct-to-elasticsearch
Keywords: pmacct,NetFlow,accounting,BGP
Platform: UNKNOWN
Classifier: Development Status :: 4 - Beta
Classifier: Environment :: Console
Classifier: Intended Audience :: Information Technology
Classifier: Intended Audience :: Science/Research
Classifier: Intended Audience :: System Administrators
Classifier: Intended Audience :: Telecommunications Industry
Classifier: Operating System :: POSIX
Classifier: Operating System :: Unix
Classifier: Programming Language :: Python :: 2.7
Classifier: Topic :: Internet :: WWW/HTTP
Classifier: Topic :: System :: Monitoring
Classifier: Topic :: System :: Networking
Classifier: Topic :: System :: Networking :: Monitoring
